endpoints/__init__.py
endpoints/__main__.py
endpoints/call.py
endpoints/client.py
endpoints/compat.py
endpoints/config.py
endpoints/exception.py
endpoints/utils.py
endpoints/decorators/__init__.py
endpoints/decorators/auth.py
endpoints/decorators/base.py
endpoints/decorators/call.py
endpoints/decorators/limit.py
endpoints/extras/__init__.py
endpoints/extras/forms.py
endpoints/extras/templates/__init__.py
endpoints/extras/templates/core.py
endpoints/extras/templates/decorators.py
endpoints/interface/__init__.py
endpoints/interface/asgi.py
endpoints/interface/base.py
endpoints/interface/wsgi.py
endpoints/reflection/__init__.py
endpoints/reflection/inspect.py
endpoints/reflection/openapi.py
endpoints-9.1.1.dist-info/licenses/LICENSE.txt
endpoints-9.1.1.dist-info/METADATA
endpoints-9.1.1.dist-info/WHEEL
endpoints-9.1.1.dist-info/entry_points.txt
endpoints-9.1.1.dist-info/top_level.txt
endpoints-9.1.1.dist-info/RECORD
