Metadata-Version: 2.4
Name: endpoints
Version: 9.1.1
Summary: Get an api up and running quickly
Author-email: Jay Marcyes <jay@marcyes.com>
License-Expression: MIT
Project-URL: Homepage, https://github.com/Jaymon/endpoints
Project-URL: Repository, https://github.com/Jaymon/endpoints
Keywords: asgi,asgi-server,wsgi,wsgi-server,api,api-server,server,framework,web-framework,REST,rest-api
Classifier: Development Status :: 5 - Production/Stable
Classifier: Environment :: Web Environment
Classifier: Intended Audience :: Developers
Classifier: Operating System :: OS Independent
Classifier: Topic :: Internet :: WWW/HTTP :: Dynamic Content :: CGI Tools/Libraries
Classifier: Programming Language :: Python :: 3
Requires-Python: >=3.10
License-File: LICENSE.txt
Requires-Dist: datatypes
Provides-Extra: tests
Requires-Dist: testdata; extra == "tests"
Requires-Dist: daphne; extra == "tests"
Provides-Extra: websockets
Requires-Dist: websocket-client; extra == "websockets"
Provides-Extra: templates
Requires-Dist: jinja2; extra == "templates"
Provides-Extra: openapi
Requires-Dist: jsonschema; extra == "openapi"
Requires-Dist: pyyaml; extra == "openapi"
Provides-Extra: orjson
Requires-Dist: orjson; extra == "orjson"
Dynamic: license-file
